{
  "nodes": [
    {
      "id": "node1",
      "caption": "h5"
    },
    {
      "id": "node2",
      "caption": "h4"
    },
    {
      "id": "node3",
      "caption": "h3"
    },
    {
      "id": "node4",
      "caption": "h2"
    },
    {
      "id": "node5",
      "caption": "h1"
    },
    {
      "id": "node6",
      "caption": "Social Health"
    },
    {
      "id": "node7",
      "caption": "Social Support"
    },
    {
      "id": "node8",
      "caption": "s1"
    },
    {
      "id": "node9",
      "caption": "s2"
    },
    {
      "id": "node10",
      "caption": "s3"
    },
    {
      "id": "node11",
      "caption": "s4"
    },
    {
      "id": "node12",
      "caption": "Quality"
    },
    {
      "id": "node13",
      "caption": "q7"
    },
    {
      "id": "node14",
      "caption": "q6"
    },
    {
      "id": "node15",
      "caption": "q5"
    },
    {
      "id": "node16",
      "caption": "q4"
    },
    {
      "id": "node17",
      "caption": "q3"
    },
    {
      "id": "node18",
      "caption": "q2"
    },
    {
      "id": "node19",
      "caption": "q1"
    }
  ],
  "edges": [
    {
      "id": "edge1",
      "from": "node6",
      "to": "node1"
    },
    {
      "id": "edge2",
      "from": "node6",
      "to": "node2"
    },
    {
      "id": "edge3",
      "from": "node6",
      "to": "node3"
    },
    {
      "id": "edge4",
      "from": "node6",
      "to": "node4"
    },
    {
      "id": "edge5",
      "from": "node6",
      "to": "node5"
    },
    {
      "id": "edge6",
      "from": "node7",
      "to": "node6"
    },
    {
      "id": "edge7",
      "from": "node7",
      "to": "node8"
    },
    {
      "id": "edge8",
      "from": "node7",
      "to": "node9"
    },
    {
      "id": "edge9",
      "from": "node7",
      "to": "node10"
    },
    {
      "id": "edge10",
      "from": "node7",
      "to": "node11"
    },
    {
      "id": "edge11",
      "from": "node6",
      "to": "node12"
    },
    {
      "id": "edge12",
      "from": "node7",
      "to": "node12"
    },
    {
      "id": "edge13",
      "from": "node12",
      "to": "node13"
    },
    {
      "id": "edge14",
      "from": "node12",
      "to": "node14"
    },
    {
      "id": "edge15",
      "from": "node12",
      "to": "node15"
    },
    {
      "id": "edge16",
      "from": "node12",
      "to": "node16"
    },
    {
      "id": "edge17",
      "from": "node12",
      "to": "node17"
    },
    {
      "id": "edge18",
      "from": "node12",
      "to": "node18"
    },
    {
      "id": "edge19",
      "from": "node12",
      "to": "node19"
    }
  ]
}