{
  "nodes": [
    {
      "id": "EWM",
      "caption": "E_{W_M}"
    },
    {
      "id": "W",
      "caption": "W"
    },
    {
      "id": "EWF",
      "caption": "E_{W_F}"
    },
    {
      "id": "ZM",
      "caption": "Z_M"
    },
    {
      "id": "ZF",
      "caption": "Z_F"
    },
    {
      "id": "XM",
      "caption": "X_M"
    },
    {
      "id": "X_prime",
      "caption": "X'"
    },
    {
      "id": "XF",
      "caption": "X_F"
    },
    {
      "id": "Z_prime",
      "caption": "Z'"
    }
  ],
  "edges": [
    {
      "id": "edge_0",
      "from": "EWM",
      "to": "W",
      "caption": ""
    },
    {
      "id": "edge_1",
      "from": "EWF",
      "to": "W",
      "caption": ""
    },
    {
      "id": "edge_2",
      "from": "ZM",
      "to": "W",
      "caption": "\u03b2"
    },
    {
      "id": "edge_3",
      "from": "ZF",
      "to": "W",
      "caption": "\u03b2"
    },
    {
      "id": "edge_4",
      "from": "XM",
      "to": "ZM",
      "caption": "\u03b1"
    },
    {
      "id": "edge_5",
      "from": "XF",
      "to": "ZF",
      "caption": "\u03b1"
    },
    {
      "id": "edge_6",
      "from": "XM",
      "to": "X_prime",
      "caption": ".5"
    },
    {
      "id": "edge_7",
      "from": "XF",
      "to": "X_prime",
      "caption": ".5"
    },
    {
      "id": "edge_8",
      "from": "X_prime",
      "to": "Z_prime",
      "caption": "\u03b1"
    }
  ],
  "secondary_edges": []
}