[
    {
        "caption": "Figure 1. Conceptual Model",
        "captionBoundary": {
            "x1": 72.02400207519531,
            "x2": 193.89739990234375,
            "y1": 279.6044616699219,
            "y2": 284.45001220703125
        },
        "figType": "Figure",
        "imageText": [],
        "name": "1",
        "page": 4,
        "regionBoundary": {
            "x1": 72.0,
            "x2": 539.04,
            "y1": 57.599999999999994,
            "y2": 258.24
        },
        "renderDpi": 150,
        "renderURL": "/mnt/disk2/dhoon/figure/structural_equation_model/1/image/W2101656646-Figure1-1.png"
    },
    {
        "caption": "Figure 2. Standardized Estimates of the SEM Model Note: Non-significant coefficient is indicated by a dashed arrow",
        "captionBoundary": {
            "x1": 72.02400207519531,
            "x2": 351.78533935546875,
            "y1": 406.1044616699219,
            "y2": 425.95001220703125
        },
        "figType": "Figure",
        "imageText": [],
        "name": "2",
        "page": 7,
        "regionBoundary": {
            "x1": 72.0,
            "x2": 529.4399999999999,
            "y1": 57.599999999999994,
            "y2": 381.12
        },
        "renderDpi": 150,
        "renderURL": "/mnt/disk2/dhoon/figure/structural_equation_model/1/image/W2101656646-Figure2-1.png"
    }
]