[
    {
        "caption": "Figure 3 Clarifying \u03b73.",
        "captionBoundary": {
            "x1": 62.702301025390625,
            "x2": 139.4823760986328,
            "y1": 721.93994140625,
            "y2": 727.8239135742188
        },
        "figType": "Figure",
        "imageText": [],
        "name": "3",
        "page": 3,
        "regionBoundary": {
            "x1": 58.559999999999995,
            "x2": 288.0,
            "y1": 225.6,
            "y2": 731.04
        },
        "renderDpi": 150,
        "renderURL": "/mnt/disk2/dhoon/figure/structural_equation_model/1/image/W2134792407-Figure3-1.png"
    }
]