{
  "nodes": [
    {
      "id": "node1",
      "caption": "Openness to change"
    },
    {
      "id": "node2",
      "caption": "Self-enhancement"
    },
    {
      "id": "node3",
      "caption": "Attitude towards entrepreneurship R\u00b2=0.22/R\u00b2=0.43"
    },
    {
      "id": "node4",
      "caption": "Subjective norms R\u00b2=0.15/R\u00b2=0.19"
    },
    {
      "id": "node5",
      "caption": "Perceived behavioral control R\u00b2=0.22/R\u00b2=0.22"
    },
    {
      "id": "node6",
      "caption": "Entrepreneurial Intentions R\u00b2=0.77/R\u00b2=0.69"
    }
  ],
  "edges": [
    {
      "id": "edge1",
      "from": "node1",
      "to": "node3"
    },
    {
      "id": "edge2",
      "from": "node1",
      "to": "node4"
    },
    {
      "id": "edge3",
      "from": "node1",
      "to": "node5"
    },
    {
      "id": "edge4",
      "from": "node2",
      "to": "node3"
    },
    {
      "id": "edge5",
      "from": "node2",
      "to": "node4"
    },
    {
      "id": "edge6",
      "from": "node2",
      "to": "node5"
    },
    {
      "id": "edge7",
      "from": "node3",
      "to": "node6"
    },
    {
      "id": "edge8",
      "from": "node5",
      "to": "node6"
    },
    {
      "id": "edge9",
      "from": "node2",
      "to": "node6"
    }
  ]
}