{
  "nodes": [
    {
      "id": "node1",
      "caption": "Posting Coins"
    },
    {
      "id": "node2",
      "caption": "Threading Beads"
    },
    {
      "id": "node3",
      "caption": "Drawing Trail"
    },
    {
      "id": "node4",
      "caption": "Catching Bean Bag"
    },
    {
      "id": "node5",
      "caption": "Throwing Bean Bag"
    },
    {
      "id": "node6",
      "caption": "One-Leg Stand"
    },
    {
      "id": "node7",
      "caption": "Walking on Toes"
    },
    {
      "id": "node8",
      "caption": "Jumping on Mats"
    },
    {
      "id": "node9",
      "caption": "Motor skills"
    },
    {
      "id": "node10",
      "caption": "Performance-based EFs"
    },
    {
      "id": "node11",
      "caption": "Rating-based EFs"
    },
    {
      "id": "node12",
      "caption": "Day/Night"
    },
    {
      "id": "node13",
      "caption": "Hand Tapping"
    },
    {
      "id": "node14",
      "caption": "Forward Corsi Block"
    },
    {
      "id": "node15",
      "caption": "Forward Digit Recall"
    },
    {
      "id": "node16",
      "caption": "Conflict task"
    },
    {
      "id": "node17",
      "caption": "BRIEF-P Inhibition"
    },
    {
      "id": "node18",
      "caption": "BRIEF-P Working memory"
    },
    {
      "id": "node19",
      "caption": "BRIEF-P Cognitive flexibility"
    }
  ],
  "edges": [
    {
      "id": "edge1",
      "from": "node9",
      "to": "node1"
    },
    {
      "id": "edge2",
      "from": "node9",
      "to": "node2"
    },
    {
      "id": "edge3",
      "from": "node9",
      "to": "node3"
    },
    {
      "id": "edge4",
      "from": "node9",
      "to": "node4"
    },
    {
      "id": "edge5",
      "from": "node9",
      "to": "node5"
    },
    {
      "id": "edge6",
      "from": "node9",
      "to": "node6"
    },
    {
      "id": "edge7",
      "from": "node9",
      "to": "node7"
    },
    {
      "id": "edge8",
      "from": "node9",
      "to": "node8"
    },
    {
      "id": "edge9",
      "from": "node10",
      "to": "node9"
    },
    {
      "id": "edge10",
      "from": "node11",
      "to": "node9"
    },
    {
      "id": "edge11",
      "from": "node10",
      "to": "node11"
    },
    {
      "id": "edge12",
      "from": "node10",
      "to": "node12"
    },
    {
      "id": "edge13",
      "from": "node10",
      "to": "node13"
    },
    {
      "id": "edge14",
      "from": "node10",
      "to": "node14"
    },
    {
      "id": "edge15",
      "from": "node10",
      "to": "node15"
    },
    {
      "id": "edge16",
      "from": "node10",
      "to": "node16"
    },
    {
      "id": "edge17",
      "from": "node11",
      "to": "node17"
    },
    {
      "id": "edge18",
      "from": "node11",
      "to": "node18"
    },
    {
      "id": "edge19",
      "from": "node11",
      "to": "node19"
    }
  ]
}