{
  "nodes": [
    {
      "id": "node1",
      "caption": "Rhizosphere-bulk"
    },
    {
      "id": "node2",
      "caption": "Plow-chisel plough-zero tillage"
    },
    {
      "id": "node3",
      "caption": "SOC"
    },
    {
      "id": "node4",
      "caption": "Invertase"
    },
    {
      "id": "node5",
      "caption": "TN"
    },
    {
      "id": "node6",
      "caption": "Urease"
    },
    {
      "id": "node7",
      "caption": "ST"
    },
    {
      "id": "node8",
      "caption": "SM"
    },
    {
      "id": "node9",
      "caption": "Diversity"
    },
    {
      "id": "node10",
      "caption": "Composition"
    },
    {
      "id": "node11",
      "caption": "Abundance"
    }
  ],
  "edges": [
    {
      "id": "edge1",
      "from": "node1",
      "to": "node3"
    },
    {
      "id": "edge2",
      "from": "node1",
      "to": "node4"
    },
    {
      "id": "edge3",
      "from": "node1",
      "to": "node5"
    },
    {
      "id": "edge4",
      "from": "node1",
      "to": "node6"
    },
    {
      "id": "edge5",
      "from": "node1",
      "to": "node7"
    },
    {
      "id": "edge6",
      "from": "node1",
      "to": "node8"
    },
    {
      "id": "edge7",
      "from": "node2",
      "to": "node3"
    },
    {
      "id": "edge8",
      "from": "node2",
      "to": "node4"
    },
    {
      "id": "edge9",
      "from": "node2",
      "to": "node5"
    },
    {
      "id": "edge10",
      "from": "node2",
      "to": "node6"
    },
    {
      "id": "edge11",
      "from": "node2",
      "to": "node7"
    },
    {
      "id": "edge12",
      "from": "node2",
      "to": "node8"
    },
    {
      "id": "edge13",
      "from": "node3",
      "to": "node9"
    },
    {
      "id": "edge14",
      "from": "node4",
      "to": "node9"
    },
    {
      "id": "edge15",
      "from": "node4",
      "to": "node10"
    },
    {
      "id": "edge16",
      "from": "node5",
      "to": "node9"
    },
    {
      "id": "edge17",
      "from": "node5",
      "to": "node10"
    },
    {
      "id": "edge18",
      "from": "node6",
      "to": "node10"
    },
    {
      "id": "edge19",
      "from": "node6",
      "to": "node11"
    },
    {
      "id": "edge20",
      "from": "node7",
      "to": "node11"
    },
    {
      "id": "edge21",
      "from": "node8",
      "to": "node11"
    }
  ]
}