{
  "nodes": [
    {
      "id": "node1",
      "caption": "Executive function t1"
    },
    {
      "id": "node2",
      "caption": "Behavioral self-regulation t1"
    },
    {
      "id": "node3",
      "caption": "School related well-being t1"
    },
    {
      "id": "node4",
      "caption": "Group allocation"
    },
    {
      "id": "node5",
      "caption": "Numeracy t1"
    },
    {
      "id": "node6",
      "caption": "Executive function t2"
    },
    {
      "id": "node7",
      "caption": "Behavioral self-regulation t2"
    },
    {
      "id": "node8",
      "caption": "School related well-being t2"
    },
    {
      "id": "node9",
      "caption": "Numeracy t2"
    }
  ],
  "edges": [
    {
      "id": "edge1",
      "from": "node1",
      "to": "node6"
    },
    {
      "id": "edge2",
      "from": "node2",
      "to": "node7"
    },
    {
      "id": "edge3",
      "from": "node3",
      "to": "node8"
    },
    {
      "id": "edge4",
      "from": "node4",
      "to": "node6"
    },
    {
      "id": "edge5",
      "from": "node4",
      "to": "node7"
    },
    {
      "id": "edge6",
      "from": "node4",
      "to": "node8"
    },
    {
      "id": "edge7",
      "from": "node4",
      "to": "node9"
    },
    {
      "id": "edge8",
      "from": "node5",
      "to": "node9"
    },
    {
      "id": "edge9",
      "from": "node6",
      "to": "node9"
    },
    {
      "id": "edge10",
      "from": "node7",
      "to": "node9"
    },
    {
      "id": "edge11",
      "from": "node8",
      "to": "node9"
    }
  ]
}