{
  "nodes": [
    {
      "id": "node1",
      "caption": "Channel Impulse Response & Coarse Range Estimation"
    },
    {
      "id": "node2",
      "caption": "Channel Type Identification Path Loss Magnitude (PL) Signal Amplitude (A) Multipath Components (MPC) RMS Delay Spread (\u03c4rms) Kurtosis (\u03ba)"
    },
    {
      "id": "node3",
      "caption": "PL<PLLOS A>ALOS \u03c4rms<\u03c4rms(LOS) MPC<MPCLOS \u03ba > \u03baLOS"
    },
    {
      "id": "node4",
      "caption": "Non-Line of Sight (NLOS) Or Partial NLOS/LOS"
    },
    {
      "id": "node5",
      "caption": "Line of Sight (LOS)"
    },
    {
      "id": "node6",
      "caption": "\u03c4rms > \u03c4rms(NLOS) \u03ba < \u03baNLOS"
    },
    {
      "id": "node7",
      "caption": "Maximum Peak Detection (LOS)"
    },
    {
      "id": "node8",
      "caption": "Leading Edge Detection Technique (NLOS)"
    },
    {
      "id": "node9",
      "caption": "Search Back Technique (Partial NLOS/LOS)"
    },
    {
      "id": "node10",
      "caption": "Accurate Range Estimation"
    },
    {
      "id": "node11",
      "caption": "Location Estimation Trilateration: Least Square Solution"
    },
    {
      "id": "node12",
      "caption": "No"
    },
    {
      "id": "node13",
      "caption": "Yes"
    },
    {
      "id": "node14",
      "caption": "No"
    },
    {
      "id": "node15",
      "caption": "Yes"
    }
  ],
  "edges": [
    {
      "id": "edge1",
      "from": "node1",
      "to": "node2"
    },
    {
      "id": "edge2",
      "from": "node2",
      "to": "node3"
    },
    {
      "id": "edge3",
      "from": "node3",
      "to": "node4"
    },
    {
      "id": "edge4",
      "from": "node3",
      "to": "node5"
    },
    {
      "id": "edge5",
      "from": "node4",
      "to": "node6"
    },
    {
      "id": "edge6",
      "from": "node5",
      "to": "node7"
    },
    {
      "id": "edge7",
      "from": "node6",
      "to": "node8"
    },
    {
      "id": "edge8",
      "from": "node6",
      "to": "node9"
    },
    {
      "id": "edge9",
      "from": "node7",
      "to": "node10"
    },
    {
      "id": "edge10",
      "from": "node8",
      "to": "node10"
    },
    {
      "id": "edge11",
      "from": "node9",
      "to": "node10"
    },
    {
      "id": "edge12",
      "from": "node10",
      "to": "node11"
    }
  ]
}