{
  "nodes": [
    {
      "id": "node1",
      "caption": "C"
    },
    {
      "id": "node2",
      "caption": "L\u2081"
    },
    {
      "id": "node3",
      "caption": "L\u2082"
    },
    {
      "id": "node4",
      "caption": "L\u2098\u208b\u2081"
    },
    {
      "id": "node5",
      "caption": "L\u2098"
    },
    {
      "id": "node6",
      "caption": "G\u2081"
    },
    {
      "id": "node7",
      "caption": "G\u2082"
    },
    {
      "id": "node8",
      "caption": "G\u2083"
    },
    {
      "id": "node9",
      "caption": "G\u2084"
    },
    {
      "id": "node10",
      "caption": "G\u2096\u208b\u2082"
    },
    {
      "id": "node11",
      "caption": "G\u2096\u208b\u2081"
    },
    {
      "id": "node12",
      "caption": "G\u2096"
    }
  ],
  "edges": [
    {
      "id": "edge1",
      "from": "node1",
      "to": "node2"
    },
    {
      "id": "edge2",
      "from": "node1",
      "to": "node3"
    },
    {
      "id": "edge3",
      "from": "node1",
      "to": "node4"
    },
    {
      "id": "edge4",
      "from": "node1",
      "to": "node5"
    },
    {
      "id": "edge5",
      "from": "node2",
      "to": "node6"
    },
    {
      "id": "edge6",
      "from": "node2",
      "to": "node7"
    },
    {
      "id": "edge7",
      "from": "node2",
      "to": "node8"
    },
    {
      "id": "edge8",
      "from": "node3",
      "to": "node7"
    },
    {
      "id": "edge9",
      "from": "node3",
      "to": "node8"
    },
    {
      "id": "edge10",
      "from": "node3",
      "to": "node9"
    },
    {
      "id": "edge11",
      "from": "node4",
      "to": "node10"
    },
    {
      "id": "edge12",
      "from": "node4",
      "to": "node11"
    },
    {
      "id": "edge13",
      "from": "node4",
      "to": "node12"
    },
    {
      "id": "edge14",
      "from": "node5",
      "to": "node12"
    }
  ]
}