{
  "nodes": [
    {
      "id": "node1",
      "caption": "1. Year of surgery 2. Age 3. Gender 4. ASA 5. Blood Hemoglobin 6. Weight loss 7. Diabetes"
    },
    {
      "id": "node2",
      "caption": "Preoperative Treatment 1. Hospital stay 2. Bowel preparation 3. Glucidic drink 4. Premedication"
    },
    {
      "id": "node3",
      "caption": "Intraoperative Treatment 1. IV fluid administration 2. Epidural anesthesia 3. Antibiotic prophylaxis 4. Normothermia 5. PONV prophylaxis 6. Surgical drainage"
    },
    {
      "id": "node4",
      "caption": "Postoperative Treatment 1. IV fluid administration 2. Morphine administration 3. Thromboembolism prophylaxis 4. Prokinetics administration 5. Early NGT removal 6. Early intravenous fluid stop 7. Early urinary catheter removal 8. Early ambulation"
    },
    {
      "id": "node5",
      "caption": "1. Fluid losses 2. Length of surgery 3. Postoperative pain 4. Laparotomy 5. Surgical stoma"
    },
    {
      "id": "node6",
      "caption": "1. Type of surgery 2. Malignancy 3. Blood transfusion"
    },
    {
      "id": "node7",
      "caption": "U(0) U(1)"
    },
    {
      "id": "node8",
      "caption": "U"
    },
    {
      "id": "node9",
      "caption": "Outcome Primary 1. Any complication 2. Medical complication 3. SSI 4. TRD after POD 5 5. Discharge after POD 6 Secondary 1. Bowel function recovery 2. IV fluids resumption 3. NGT replacement 4. PONV occurrence 5. Surgical re-intervention 6. Hospital re-admission 7. Death within POD 30"
    }
  ],
  "edges": [
    {
      "id": "edge1",
      "from": "node1",
      "to": "node2"
    },
    {
      "id": "edge2",
      "from": "node1",
      "to": "node3"
    },
    {
      "id": "edge3",
      "from": "node1",
      "to": "node4"
    },
    {
      "id": "edge4",
      "from": "node1",
      "to": "node7"
    },
    {
      "id": "edge5",
      "from": "node2",
      "to": "node8"
    },
    {
      "id": "edge6",
      "from": "node3",
      "to": "node8"
    },
    {
      "id": "edge7",
      "from": "node4",
      "to": "node8"
    },
    {
      "id": "edge8",
      "from": "node5",
      "to": "node4"
    },
    {
      "id": "edge9",
      "from": "node5",
      "to": "node8"
    },
    {
      "id": "edge10",
      "from": "node6",
      "to": "node7"
    },
    {
      "id": "edge11",
      "from": "node7",
      "to": "node8"
    },
    {
      "id": "edge12",
      "from": "node8",
      "to": "node9"
    }
  ]
}