{
  "nodes": [
    {
      "id": "node1",
      "caption": "X1"
    },
    {
      "id": "node2",
      "caption": "X2"
    },
    {
      "id": "node3",
      "caption": "A1"
    },
    {
      "id": "node4",
      "caption": "X3"
    },
    {
      "id": "node5",
      "caption": "X4"
    },
    {
      "id": "node6",
      "caption": "A2"
    },
    {
      "id": "node7",
      "caption": "T"
    },
    {
      "id": "node8",
      "caption": "S1"
    },
    {
      "id": "node9",
      "caption": "S2"
    },
    {
      "id": "node10",
      "caption": "C1"
    },
    {
      "id": "node11",
      "caption": "C2"
    },
    {
      "id": "node12",
      "caption": "C3"
    },
    {
      "id": "node13",
      "caption": "C4"
    }
  ],
  "edges": [
    {
      "id": "edge1",
      "from": "node1",
      "to": "node3"
    },
    {
      "id": "edge2",
      "from": "node2",
      "to": "node3"
    },
    {
      "id": "edge3",
      "from": "node3",
      "to": "node7"
    },
    {
      "id": "edge4",
      "from": "node4",
      "to": "node6"
    },
    {
      "id": "edge5",
      "from": "node5",
      "to": "node6"
    },
    {
      "id": "edge6",
      "from": "node6",
      "to": "node7"
    },
    {
      "id": "edge7",
      "from": "node7",
      "to": "node8"
    },
    {
      "id": "edge8",
      "from": "node8",
      "to": "node9"
    },
    {
      "id": "edge9",
      "from": "node9",
      "to": "node10"
    },
    {
      "id": "edge10",
      "from": "node9",
      "to": "node11"
    },
    {
      "id": "edge11",
      "from": "node8",
      "to": "node12"
    },
    {
      "id": "edge12",
      "from": "node8",
      "to": "node13"
    }
  ]
}