{
  "nodes": [
    {
      "id": "node1",
      "caption": "Perceived quality"
    },
    {
      "id": "node2",
      "caption": "Brand salience"
    },
    {
      "id": "node3",
      "caption": "Brand loyalty"
    },
    {
      "id": "node4",
      "caption": "Brand image"
    }
  ],
  "edges": [
    {
      "id": "edge1",
      "from": "node2",
      "to": "node1"
    },
    {
      "id": "edge2",
      "from": "node2",
      "to": "node3"
    },
    {
      "id": "edge3",
      "from": "node2",
      "to": "node4"
    },
    {
      "id": "edge4",
      "from": "node1",
      "to": "node3"
    },
    {
      "id": "edge5",
      "from": "node1",
      "to": "node4"
    },
    {
      "id": "edge6",
      "from": "node4",
      "to": "node3"
    }
  ]
}