{
  "nodes": [
    {
      "id": "node1",
      "caption": "Run"
    },
    {
      "id": "node2",
      "caption": "Gallop"
    },
    {
      "id": "node3",
      "caption": "Hop"
    },
    {
      "id": "node4",
      "caption": "Leap"
    },
    {
      "id": "node5",
      "caption": "Jump"
    },
    {
      "id": "node6",
      "caption": "Slide"
    },
    {
      "id": "node7",
      "caption": "Locomotive"
    },
    {
      "id": "node8",
      "caption": "Strike"
    },
    {
      "id": "node9",
      "caption": "Dribble"
    },
    {
      "id": "node10",
      "caption": "Catch"
    },
    {
      "id": "node11",
      "caption": "Throw"
    },
    {
      "id": "node12",
      "caption": "Kick"
    },
    {
      "id": "node13",
      "caption": "Under Arm Roll"
    },
    {
      "id": "node14",
      "caption": "Object Control"
    },
    {
      "id": "node15",
      "caption": "Log Roll"
    },
    {
      "id": "node16",
      "caption": "Rock"
    },
    {
      "id": "node17",
      "caption": "Back Support"
    },
    {
      "id": "node18",
      "caption": "Stability Skills"
    },
    {
      "id": "node19",
      "caption": "Fundamental Movement Skills"
    }
  ],
  "edges": [
    {
      "id": "edge1",
      "from": "node7",
      "to": "node1"
    },
    {
      "id": "edge2",
      "from": "node7",
      "to": "node2"
    },
    {
      "id": "edge3",
      "from": "node7",
      "to": "node3"
    },
    {
      "id": "edge4",
      "from": "node7",
      "to": "node4"
    },
    {
      "id": "edge5",
      "from": "node7",
      "to": "node5"
    },
    {
      "id": "edge6",
      "from": "node7",
      "to": "node6"
    },
    {
      "id": "edge7",
      "from": "node14",
      "to": "node8"
    },
    {
      "id": "edge8",
      "from": "node14",
      "to": "node9"
    },
    {
      "id": "edge9",
      "from": "node14",
      "to": "node10"
    },
    {
      "id": "edge10",
      "from": "node14",
      "to": "node11"
    },
    {
      "id": "edge11",
      "from": "node14",
      "to": "node12"
    },
    {
      "id": "edge12",
      "from": "node14",
      "to": "node13"
    },
    {
      "id": "edge13",
      "from": "node18",
      "to": "node15"
    },
    {
      "id": "edge14",
      "from": "node18",
      "to": "node16"
    },
    {
      "id": "edge15",
      "from": "node18",
      "to": "node17"
    },
    {
      "id": "edge16",
      "from": "node19",
      "to": "node7"
    },
    {
      "id": "edge17",
      "from": "node19",
      "to": "node14"
    },
    {
      "id": "edge18",
      "from": "node19",
      "to": "node18"
    }
  ]
}