{
  "nodes": [
    {
      "id": "node1",
      "caption": "F"
    },
    {
      "id": "node2",
      "caption": "A"
    },
    {
      "id": "node3",
      "caption": "P_F"
    },
    {
      "id": "node4",
      "caption": "D"
    },
    {
      "id": "node5",
      "caption": "E"
    },
    {
      "id": "node6",
      "caption": "P_M"
    },
    {
      "id": "node7",
      "caption": "P_T1"
    },
    {
      "id": "node8",
      "caption": "P_T2"
    },
    {
      "id": "node9",
      "caption": "P_Sib"
    }
  ],
  "edges": [
    {
      "id": "edge1",
      "from": "node1",
      "to": "node2"
    },
    {
      "id": "edge2",
      "from": "node2",
      "to": "node3"
    },
    {
      "id": "edge3",
      "from": "node4",
      "to": "node3"
    },
    {
      "id": "edge4",
      "from": "node5",
      "to": "node3"
    },
    {
      "id": "edge5",
      "from": "node1",
      "to": "node3"
    },
    {
      "id": "edge6",
      "from": "node1",
      "to": "node6"
    },
    {
      "id": "edge7",
      "from": "node4",
      "to": "node6"
    },
    {
      "id": "edge8",
      "from": "node5",
      "to": "node6"
    },
    {
      "id": "edge9",
      "from": "node2",
      "to": "node6"
    },
    {
      "id": "edge10",
      "from": "node1",
      "to": "node7"
    },
    {
      "id": "edge11",
      "from": "node2",
      "to": "node7"
    },
    {
      "id": "edge12",
      "from": "node5",
      "to": "node7"
    },
    {
      "id": "edge13",
      "from": "node4",
      "to": "node7"
    },
    {
      "id": "edge14",
      "from": "node1",
      "to": "node8"
    },
    {
      "id": "edge15",
      "from": "node2",
      "to": "node8"
    },
    {
      "id": "edge16",
      "from": "node5",
      "to": "node8"
    },
    {
      "id": "edge17",
      "from": "node4",
      "to": "node8"
    },
    {
      "id": "edge18",
      "from": "node1",
      "to": "node9"
    },
    {
      "id": "edge19",
      "from": "node2",
      "to": "node9"
    },
    {
      "id": "edge20",
      "from": "node5",
      "to": "node9"
    },
    {
      "id": "edge21",
      "from": "node4",
      "to": "node9"
    }
  ]
}