{
  "nodes": [
    {
      "id": "node1",
      "caption": "Initial Fault List Generation"
    },
    {
      "id": "node2",
      "caption": "Test Cube Generation with Dynamic Compaction"
    },
    {
      "id": "node3",
      "caption": "Test Cube \u2192 C1"
    },
    {
      "id": "node4",
      "caption": "Detection-Oriented X-Filling (e.g., Random-Fill)"
    },
    {
      "id": "node5",
      "caption": "Test Vector \u2192 V"
    },
    {
      "id": "node6",
      "caption": "Path Classification"
    },
    {
      "id": "node7",
      "caption": "Any Hot Paths?"
    },
    {
      "id": "node8",
      "caption": "X-Restoration for Hot Paths"
    },
    {
      "id": "node9",
      "caption": "Test Cube \u2192 C2"
    },
    {
      "id": "node10",
      "caption": "X-Filling for Reducing Capture Power"
    },
    {
      "id": "node11",
      "caption": "Test Vector \u2192 V"
    },
    {
      "id": "node12",
      "caption": "Any Remaining Hot Paths?"
    },
    {
      "id": "node13",
      "caption": "Remaining Hot Path Masking"
    },
    {
      "id": "node14",
      "caption": "Any Cold Paths?"
    },
    {
      "id": "node15",
      "caption": "X-Restoration for Cold Paths"
    },
    {
      "id": "node16",
      "caption": "Test Cube \u2192 C3"
    },
    {
      "id": "node17",
      "caption": "X-Filling for Increasing Capture Power"
    },
    {
      "id": "node18",
      "caption": "Test Vector \u2192 V"
    },
    {
      "id": "node19",
      "caption": "V: Final Test Vector"
    },
    {
      "id": "node20",
      "caption": "Fault Simulation for V to Update Fault List"
    },
    {
      "id": "node21",
      "caption": "Termination Condition Met ?"
    }
  ],
  "edges": [
    {
      "id": "edge1",
      "from": "node1",
      "to": "node2"
    },
    {
      "id": "edge2",
      "from": "node2",
      "to": "node3"
    },
    {
      "id": "edge3",
      "from": "node3",
      "to": "node4"
    },
    {
      "id": "edge4",
      "from": "node4",
      "to": "node5"
    },
    {
      "id": "edge5",
      "from": "node5",
      "to": "node6"
    },
    {
      "id": "edge6",
      "from": "node6",
      "to": "node7"
    },
    {
      "id": "edge7",
      "from": "node7",
      "to": "node8"
    },
    {
      "id": "edge8",
      "from": "node8",
      "to": "node9"
    },
    {
      "id": "edge9",
      "from": "node9",
      "to": "node10"
    },
    {
      "id": "edge10",
      "from": "node10",
      "to": "node11"
    },
    {
      "id": "edge11",
      "from": "node11",
      "to": "node12"
    },
    {
      "id": "edge12",
      "from": "node12",
      "to": "node13"
    },
    {
      "id": "edge13",
      "from": "node13",
      "to": "node14"
    },
    {
      "id": "edge14",
      "from": "node7",
      "to": "node14"
    },
    {
      "id": "edge15",
      "from": "node12",
      "to": "node14"
    },
    {
      "id": "edge16",
      "from": "node14",
      "to": "node15"
    },
    {
      "id": "edge17",
      "from": "node15",
      "to": "node16"
    },
    {
      "id": "edge18",
      "from": "node16",
      "to": "node17"
    },
    {
      "id": "edge19",
      "from": "node17",
      "to": "node18"
    },
    {
      "id": "edge20",
      "from": "node18",
      "to": "node19"
    },
    {
      "id": "edge21",
      "from": "node14",
      "to": "node19"
    },
    {
      "id": "edge22",
      "from": "node19",
      "to": "node20"
    },
    {
      "id": "edge23",
      "from": "node20",
      "to": "node21"
    },
    {
      "id": "edge24",
      "from": "node21",
      "to": "node2"
    }
  ]
}