{
  "nodes": [
    {
      "id": "node1",
      "caption": "Forecasting Efforts"
    },
    {
      "id": "node2",
      "caption": "Early Warning"
    },
    {
      "id": "node3",
      "caption": "DISASTER EVENT"
    },
    {
      "id": "node4",
      "caption": "DISASTER IMPACT ANALYSIS Nature Intensity Scope"
    },
    {
      "id": "node5",
      "caption": "NEEDS ASSESSMENT AND APPEALS Short term | Long term"
    },
    {
      "id": "node6",
      "caption": "RESTORATION & RECONSTRUCTION"
    },
    {
      "id": "node7",
      "caption": "PREPAREDNESS Communication plans Intervention plans Multi-agency coordination Maintenance Training & sensitization"
    },
    {
      "id": "node8",
      "caption": "EMERGENCY RESPONSE Mobilization of resources Primary procurement Immediate assistance/humanitarian aid Priority rehabilitation"
    },
    {
      "id": "node9",
      "caption": "MITIGATION Identifying potential hazards Evaluating potential hazards Development of structural & non-structural measures"
    }
  ],
  "edges": [
    {
      "id": "edge1",
      "from": "node1",
      "to": "node2"
    },
    {
      "id": "edge2",
      "from": "node2",
      "to": "node3"
    },
    {
      "id": "edge3",
      "from": "node3",
      "to": "node4"
    },
    {
      "id": "edge4",
      "from": "node4",
      "to": "node5"
    },
    {
      "id": "edge5",
      "from": "node5",
      "to": "node6"
    },
    {
      "id": "edge6",
      "from": "node6",
      "to": "node1"
    },
    {
      "id": "edge7",
      "from": "node7",
      "to": "node3"
    },
    {
      "id": "edge8",
      "from": "node3",
      "to": "node7"
    },
    {
      "id": "edge9",
      "from": "node5",
      "to": "node8"
    },
    {
      "id": "edge10",
      "from": "node8",
      "to": "node6"
    },
    {
      "id": "edge11",
      "from": "node9",
      "to": "node1"
    },
    {
      "id": "edge12",
      "from": "node1",
      "to": "node9"
    },
    {
      "id": "edge13",
      "from": "node9",
      "to": "node7"
    },
    {
      "id": "edge14",
      "from": "node7",
      "to": "node9"
    }
  ]
}