{
  "nodes": [
    {
      "id": "node1",
      "caption": "FAI1"
    },
    {
      "id": "node2",
      "caption": "FAI2"
    },
    {
      "id": "node3",
      "caption": "Gender"
    },
    {
      "id": "node4",
      "caption": "Sub optimal parenting"
    },
    {
      "id": "node5",
      "caption": "DSM-IV diagnosis"
    },
    {
      "id": "node6",
      "caption": "Parent conflict"
    },
    {
      "id": "node7",
      "caption": "IQ"
    }
  ],
  "edges": [
    {
      "id": "edge1",
      "from": "node1",
      "to": "node4"
    },
    {
      "id": "edge2",
      "from": "node1",
      "to": "node5"
    },
    {
      "id": "edge3",
      "from": "node2",
      "to": "node4"
    },
    {
      "id": "edge4",
      "from": "node2",
      "to": "node6"
    },
    {
      "id": "edge5",
      "from": "node3",
      "to": "node4"
    },
    {
      "id": "edge6",
      "from": "node3",
      "to": "node5"
    },
    {
      "id": "edge7",
      "from": "node3",
      "to": "node6"
    },
    {
      "id": "edge8",
      "from": "node4",
      "to": "node5"
    },
    {
      "id": "edge9",
      "from": "node4",
      "to": "node7"
    },
    {
      "id": "edge10",
      "from": "node5",
      "to": "node7"
    },
    {
      "id": "edge11",
      "from": "node6",
      "to": "node5"
    },
    {
      "id": "edge12",
      "from": "node6",
      "to": "node7"
    },
    {
      "id": "edge13",
      "from": "node7",
      "to": "node5"
    }
  ]
}