{
  "nodes": [
    {
      "id": "node1",
      "caption": "System Quality"
    },
    {
      "id": "node2",
      "caption": "Information Quality"
    },
    {
      "id": "node3",
      "caption": "Service Quality"
    },
    {
      "id": "node4",
      "caption": "Student Attitude"
    },
    {
      "id": "node5",
      "caption": "Course quality"
    },
    {
      "id": "node6",
      "caption": "Self-regulated learning"
    }
  ],
  "edges": [
    {
      "id": "edge1",
      "from": "node1",
      "to": "node6"
    },
    {
      "id": "edge2",
      "from": "node2",
      "to": "node6"
    },
    {
      "id": "edge3",
      "from": "node3",
      "to": "node6"
    },
    {
      "id": "edge4",
      "from": "node4",
      "to": "node6"
    },
    {
      "id": "edge5",
      "from": "node5",
      "to": "node6"
    }
  ]
}