{
  "nodes": [
    {
      "id": "node1",
      "caption": "Mutual benefit of participants"
    },
    {
      "id": "node2",
      "caption": "Alma mater continues to play a liaison role"
    },
    {
      "id": "node3",
      "caption": "Government provides policy support"
    },
    {
      "id": "node4",
      "caption": "Obvious alumni investment returns"
    },
    {
      "id": "node5",
      "caption": "Gains of alma mater"
    },
    {
      "id": "node6",
      "caption": "Promote urban economic development"
    },
    {
      "id": "node7",
      "caption": "Keep in touch with key alumni"
    },
    {
      "id": "node8",
      "caption": "Maintain interaction with alumni associations"
    },
    {
      "id": "node9",
      "caption": "Combine returning to school activities with alumni returning economy"
    },
    {
      "id": "node10",
      "caption": "Support related universities"
    },
    {
      "id": "node11",
      "caption": "Optimize investment policy"
    },
    {
      "id": "node12",
      "caption": "Focus on policy implementation and follow-up"
    },
    {
      "id": "node13",
      "caption": "Enrich alumni association activities"
    },
    {
      "id": "node14",
      "caption": "Enhance communication with other university alumni associations"
    },
    {
      "id": "node15",
      "caption": "Build an inter-city economic cooperation system with alumni as a link"
    },
    {
      "id": "node16",
      "caption": "Perfect the cooperation system between enterprises and universities"
    },
    {
      "id": "node17",
      "caption": "Integrate universities and alumni into industrial layout strategy"
    },
    {
      "id": "node18",
      "caption": "Increase and improve the entry point of alumni economy"
    },
    {
      "id": "node19",
      "caption": "Fix the frequency of related activities"
    },
    {
      "id": "node20",
      "caption": "Focus on promotional activities"
    },
    {
      "id": "node21",
      "caption": "Expand activity depth and breadth and form closed loop"
    },
    {
      "id": "node22",
      "caption": "Promote the development of alumni economy"
    },
    {
      "id": "node23",
      "caption": "Maintain vitality and stickiness of alumni association"
    },
    {
      "id": "node24",
      "caption": "Provide a diversified cooperation platform"
    },
    {
      "id": "node25",
      "caption": "Build related brand activities"
    }
  ],
  "edges": [
    {
      "id": "edge1",
      "from": "node4",
      "to": "node1"
    },
    {
      "id": "edge2",
      "from": "node5",
      "to": "node1"
    },
    {
      "id": "edge3",
      "from": "node6",
      "to": "node1"
    },
    {
      "id": "edge4",
      "from": "node7",
      "to": "node2"
    },
    {
      "id": "edge5",
      "from": "node8",
      "to": "node2"
    },
    {
      "id": "edge6",
      "from": "node9",
      "to": "node2"
    },
    {
      "id": "edge7",
      "from": "node10",
      "to": "node3"
    },
    {
      "id": "edge8",
      "from": "node11",
      "to": "node3"
    },
    {
      "id": "edge9",
      "from": "node12",
      "to": "node3"
    },
    {
      "id": "edge10",
      "from": "node1",
      "to": "node22"
    },
    {
      "id": "edge11",
      "from": "node2",
      "to": "node22"
    },
    {
      "id": "edge12",
      "from": "node3",
      "to": "node22"
    },
    {
      "id": "edge13",
      "from": "node13",
      "to": "node16"
    },
    {
      "id": "edge14",
      "from": "node14",
      "to": "node17"
    },
    {
      "id": "edge15",
      "from": "node15",
      "to": "node18"
    },
    {
      "id": "edge16",
      "from": "node16",
      "to": "node24"
    },
    {
      "id": "edge17",
      "from": "node17",
      "to": "node24"
    },
    {
      "id": "edge18",
      "from": "node18",
      "to": "node24"
    },
    {
      "id": "edge19",
      "from": "node19",
      "to": "node25"
    },
    {
      "id": "edge20",
      "from": "node20",
      "to": "node25"
    },
    {
      "id": "edge21",
      "from": "node21",
      "to": "node25"
    },
    {
      "id": "edge22",
      "from": "node23",
      "to": "node1"
    },
    {
      "id": "edge23",
      "from": "node24",
      "to": "node2"
    },
    {
      "id": "edge24",
      "from": "node25",
      "to": "node3"
    }
  ]
}