{
  "nodes": [
    {
      "id": "node1",
      "caption": "Autonomy"
    },
    {
      "id": "node2",
      "caption": "Competence"
    },
    {
      "id": "node3",
      "caption": "Relatedness"
    },
    {
      "id": "node4",
      "caption": "Need Satisfaction"
    },
    {
      "id": "node5",
      "caption": "Salience"
    },
    {
      "id": "node6",
      "caption": "Excessive Use"
    },
    {
      "id": "node7",
      "caption": "Neglect of Work"
    },
    {
      "id": "node8",
      "caption": "Anticipation"
    },
    {
      "id": "node9",
      "caption": "Lack of Control"
    },
    {
      "id": "node10",
      "caption": "Neglect of Social Life"
    },
    {
      "id": "node11",
      "caption": "Problematic Internet Use"
    },
    {
      "id": "node12",
      "caption": "Depression"
    },
    {
      "id": "node13",
      "caption": "Anxiety"
    },
    {
      "id": "node14",
      "caption": "Stress"
    },
    {
      "id": "node15",
      "caption": "Psychological Distress"
    }
  ],
  "edges": [
    {
      "id": "edge1",
      "from": "node4",
      "to": "node1"
    },
    {
      "id": "edge2",
      "from": "node4",
      "to": "node2"
    },
    {
      "id": "edge3",
      "from": "node4",
      "to": "node3"
    },
    {
      "id": "edge4",
      "from": "node11",
      "to": "node5"
    },
    {
      "id": "edge5",
      "from": "node11",
      "to": "node6"
    },
    {
      "id": "edge6",
      "from": "node11",
      "to": "node7"
    },
    {
      "id": "edge7",
      "from": "node11",
      "to": "node8"
    },
    {
      "id": "edge8",
      "from": "node11",
      "to": "node9"
    },
    {
      "id": "edge9",
      "from": "node11",
      "to": "node10"
    },
    {
      "id": "edge10",
      "from": "node15",
      "to": "node12"
    },
    {
      "id": "edge11",
      "from": "node15",
      "to": "node13"
    },
    {
      "id": "edge12",
      "from": "node15",
      "to": "node14"
    },
    {
      "id": "edge13",
      "from": "node4",
      "to": "node11"
    },
    {
      "id": "edge14",
      "from": "node11",
      "to": "node15"
    },
    {
      "id": "edge15",
      "from": "node4",
      "to": "node15"
    }
  ]
}