{
  "nodes": [
    {
      "id": "node1",
      "caption": "Occup_PAHs"
    },
    {
      "id": "node2",
      "caption": "DNAmAge"
    },
    {
      "id": "node3",
      "caption": "Chronic diseases"
    },
    {
      "id": "node4",
      "caption": "Outdoor"
    },
    {
      "id": "node5",
      "caption": "Indoor"
    },
    {
      "id": "node6",
      "caption": "Diet"
    },
    {
      "id": "node7",
      "caption": "Environ_PAHs"
    },
    {
      "id": "node8",
      "caption": "nDNA_changes"
    },
    {
      "id": "node9",
      "caption": "MN"
    },
    {
      "id": "node10",
      "caption": "Anti-BPDE-DNA adducts"
    },
    {
      "id": "node11",
      "caption": "p53"
    },
    {
      "id": "node12",
      "caption": "p16"
    },
    {
      "id": "node13",
      "caption": "IL-6"
    },
    {
      "id": "node14",
      "caption": "HICI"
    },
    {
      "id": "node15",
      "caption": "LINE-1"
    },
    {
      "id": "node16",
      "caption": "Alu"
    },
    {
      "id": "node17",
      "caption": "GSTM1"
    }
  ],
  "edges": [
    {
      "id": "edge1",
      "from": "node1",
      "to": "node2"
    },
    {
      "id": "edge2",
      "from": "node3",
      "to": "node2"
    },
    {
      "id": "edge3",
      "from": "node4",
      "to": "node7"
    },
    {
      "id": "edge4",
      "from": "node5",
      "to": "node7"
    },
    {
      "id": "edge5",
      "from": "node6",
      "to": "node7"
    },
    {
      "id": "edge6",
      "from": "node7",
      "to": "node2"
    },
    {
      "id": "edge7",
      "from": "node1",
      "to": "node8"
    },
    {
      "id": "edge8",
      "from": "node7",
      "to": "node8"
    },
    {
      "id": "edge9",
      "from": "node8",
      "to": "node2"
    },
    {
      "id": "edge10",
      "from": "node8",
      "to": "node9"
    },
    {
      "id": "edge11",
      "from": "node8",
      "to": "node10"
    },
    {
      "id": "edge12",
      "from": "node8",
      "to": "node11"
    },
    {
      "id": "edge13",
      "from": "node8",
      "to": "node12"
    },
    {
      "id": "edge14",
      "from": "node8",
      "to": "node13"
    },
    {
      "id": "edge15",
      "from": "node8",
      "to": "node14"
    },
    {
      "id": "edge16",
      "from": "node8",
      "to": "node15"
    },
    {
      "id": "edge17",
      "from": "node8",
      "to": "node16"
    },
    {
      "id": "edge18",
      "from": "node8",
      "to": "node17"
    }
  ]
}