{
  "nodes": [
    {
      "id": "node1",
      "caption": "Code execution"
    },
    {
      "id": "node2",
      "caption": "Authentication bypass"
    },
    {
      "id": "node3",
      "caption": "Privilege escalation"
    },
    {
      "id": "node4",
      "caption": "data leakage"
    },
    {
      "id": "node5",
      "caption": "DDoS"
    }
  ],
  "edges": [
    {
      "id": "edge1",
      "from": "node1",
      "to": "node2"
    },
    {
      "id": "edge2",
      "from": "node2",
      "to": "node3"
    },
    {
      "id": "edge3",
      "from": "node3",
      "to": "node4"
    },
    {
      "id": "edge4",
      "from": "node3",
      "to": "node5"
    }
  ]
}