{
  "nodes": [
    {
      "id": "node1",
      "caption": "Positive Metacognitive Beliefs about Desire Thinking"
    },
    {
      "id": "node2",
      "caption": "Desire Thinking: Imaginal Prefiguration"
    },
    {
      "id": "node3",
      "caption": "Desire Thinking: Verbal Perseverance"
    },
    {
      "id": "node4",
      "caption": "Depression"
    },
    {
      "id": "node5",
      "caption": "Anger"
    },
    {
      "id": "node6",
      "caption": "Craving"
    },
    {
      "id": "node7",
      "caption": "Negative Metacognitive Beliefs about Desire Thinking"
    },
    {
      "id": "node8",
      "caption": "Anxiety"
    }
  ],
  "edges": [
    {
      "id": "edge1",
      "from": "node1",
      "to": "node2"
    },
    {
      "id": "edge2",
      "from": "node1",
      "to": "node3"
    },
    {
      "id": "edge3",
      "from": "node1",
      "to": "node4"
    },
    {
      "id": "edge4",
      "from": "node2",
      "to": "node3"
    },
    {
      "id": "edge5",
      "from": "node2",
      "to": "node5"
    },
    {
      "id": "edge6",
      "from": "node3",
      "to": "node5"
    },
    {
      "id": "edge7",
      "from": "node3",
      "to": "node6"
    },
    {
      "id": "edge8",
      "from": "node3",
      "to": "node7"
    },
    {
      "id": "edge9",
      "from": "node4",
      "to": "node5"
    },
    {
      "id": "edge10",
      "from": "node4",
      "to": "node8"
    },
    {
      "id": "edge11",
      "from": "node5",
      "to": "node8"
    },
    {
      "id": "edge12",
      "from": "node6",
      "to": "node7"
    },
    {
      "id": "edge13",
      "from": "node8",
      "to": "node7"
    }
  ]
}