{
  "nodes": [
    {
      "id": "node1",
      "caption": "X"
    },
    {
      "id": "node2",
      "caption": "z"
    },
    {
      "id": "node3",
      "caption": "y"
    },
    {
      "id": "node4",
      "caption": "A"
    },
    {
      "id": "node5",
      "caption": "\u03a9"
    },
    {
      "id": "node6",
      "caption": "\u03b9"
    },
    {
      "id": "node7",
      "caption": "P"
    },
    {
      "id": "node8",
      "caption": "B"
    },
    {
      "id": "node9",
      "caption": "\u03a3"
    },
    {
      "id": "node10",
      "caption": "\u03bd"
    },
    {
      "id": "node11",
      "caption": "Q"
    },
    {
      "id": "node12",
      "caption": "\u0393"
    },
    {
      "id": "node13",
      "caption": "D"
    },
    {
      "id": "node14",
      "caption": "\u03b6"
    },
    {
      "id": "node15",
      "caption": "\u03a8"
    },
    {
      "id": "node16",
      "caption": "C"
    },
    {
      "id": "node17",
      "caption": "\u03ba"
    }
  ],
  "edges": [
    {
      "id": "edge1",
      "from": "node1",
      "to": "node2"
    },
    {
      "id": "edge2",
      "from": "node2",
      "to": "node3"
    },
    {
      "id": "edge3",
      "from": "node4",
      "to": "node5"
    },
    {
      "id": "edge4",
      "from": "node6",
      "to": "node5"
    },
    {
      "id": "edge5",
      "from": "node5",
      "to": "node2"
    },
    {
      "id": "edge6",
      "from": "node7",
      "to": "node2"
    },
    {
      "id": "edge7",
      "from": "node8",
      "to": "node9"
    },
    {
      "id": "edge8",
      "from": "node10",
      "to": "node9"
    },
    {
      "id": "edge9",
      "from": "node9",
      "to": "node7"
    },
    {
      "id": "edge10",
      "from": "node11",
      "to": "node3"
    },
    {
      "id": "edge11",
      "from": "node12",
      "to": "node11"
    },
    {
      "id": "edge12",
      "from": "node13",
      "to": "node12"
    },
    {
      "id": "edge13",
      "from": "node14",
      "to": "node12"
    },
    {
      "id": "edge14",
      "from": "node15",
      "to": "node3"
    },
    {
      "id": "edge15",
      "from": "node16",
      "to": "node15"
    },
    {
      "id": "edge16",
      "from": "node17",
      "to": "node15"
    }
  ]
}