{
  "nodes": [
    {
      "id": "node1",
      "caption": "Emotional regulation ability"
    },
    {
      "id": "node2",
      "caption": "Avoiding"
    },
    {
      "id": "node3",
      "caption": "Dominating"
    },
    {
      "id": "node4",
      "caption": "Compromising"
    },
    {
      "id": "node5",
      "caption": "Obliging"
    },
    {
      "id": "node6",
      "caption": "Integrating"
    }
  ],
  "edges": [
    {
      "id": "edge1",
      "from": "node1",
      "to": "node2"
    },
    {
      "id": "edge2",
      "from": "node1",
      "to": "node3"
    },
    {
      "id": "edge3",
      "from": "node1",
      "to": "node4"
    },
    {
      "id": "edge4",
      "from": "node1",
      "to": "node5"
    },
    {
      "id": "edge5",
      "from": "node1",
      "to": "node6"
    }
  ]
}