{
  "nodes": [
    {
      "id": "node1",
      "caption": "SP usage"
    },
    {
      "id": "node2",
      "caption": "Age"
    },
    {
      "id": "node3",
      "caption": "Gender"
    },
    {
      "id": "node4",
      "caption": "Closeness to SP"
    },
    {
      "id": "node5",
      "caption": "Trust in SP"
    },
    {
      "id": "node6",
      "caption": "SP coping with stress"
    },
    {
      "id": "node7",
      "caption": "Preoccupation with SP"
    },
    {
      "id": "node8",
      "caption": "Stress from SP"
    }
  ],
  "edges": [
    {
      "id": "edge1",
      "from": "node1",
      "to": "node6"
    },
    {
      "id": "edge2",
      "from": "node4",
      "to": "node5"
    },
    {
      "id": "edge3",
      "from": "node4",
      "to": "node7"
    },
    {
      "id": "edge4",
      "from": "node5",
      "to": "node6"
    },
    {
      "id": "edge5",
      "from": "node5",
      "to": "node7"
    },
    {
      "id": "edge6",
      "from": "node5",
      "to": "node8"
    },
    {
      "id": "edge7",
      "from": "node7",
      "to": "node6"
    },
    {
      "id": "edge8",
      "from": "node7",
      "to": "node8"
    },
    {
      "id": "edge9",
      "from": "node8",
      "to": "node6"
    },
    {
      "id": "edge10",
      "from": "node6",
      "to": "node8"
    }
  ]
}